extended_lengyel/__init__.py
extended_lengyel/adas_data.py
extended_lengyel/cli.py
extended_lengyel/config.py
extended_lengyel/curve_fit.yml
extended_lengyel/directories.py
extended_lengyel/extended_lengyel_model/Lengyel_model_basic.py
extended_lengyel/extended_lengyel_model/Lengyel_model_core.py
extended_lengyel/extended_lengyel_model/Lengyel_model_extended_S.py
extended_lengyel/extended_lengyel_model/Lengyel_model_extended_S_Zeff.py
extended_lengyel/extended_lengyel_model/Lengyel_model_extended_S_Zeff_alphat.py
extended_lengyel/extended_lengyel_model/__init__.py
extended_lengyel/extended_lengyel_model/convective_loss_fits.py
extended_lengyel/extended_lengyel_model/power_loss.py
extended_lengyel/extended_lengyel_model/upstream_temp.py
extended_lengyel/extended_units.yaml
extended_lengyel/initialize.py
extended_lengyel/kallenbach_model/__init__.py
extended_lengyel/kallenbach_model/idl_translation.py
extended_lengyel/kallenbach_model/kallenbach_model.py
extended_lengyel/kallenbach_model/kallenbach_ode.py
extended_lengyel/kallenbach_model/kallenbach_to_cc.py
extended_lengyel/kallenbach_model/reference_data/__init__.py
extended_lengyel/kallenbach_model/reference_data/kallenbach_figure_4.yaml
extended_lengyel/kallenbach_model/reference_data/read_reference_data.py
extended_lengyel/mavrin_data.py
extended_lengyel/postprocess.py
extended_lengyel/spatial_lengyel_model/__init__.py
extended_lengyel/spatial_lengyel_model/spatial_lengyel_model.py
extended_lengyel/spatial_lengyel_model/spatial_lengyel_ode.py
extended_lengyel/xr_helpers.py
extended_lengyel-0.1.3.dist-info/LICENSE
extended_lengyel-0.1.3.dist-info/METADATA
extended_lengyel-0.1.3.dist-info/WHEEL
extended_lengyel-0.1.3.dist-info/entry_points.txt
extended_lengyel-0.1.3.dist-info/RECORD
