Metadata-Version: 2.1
Name: extended_lengyel
Version: 0.1.3
Summary: 
Author: Commonwealth Fusion Systems
Requires-Python: >=3.12
Classifier: Development Status :: 5 - Production/Stable
Classifier: Intended Audience :: Science/Research
Classifier: License :: OSI Approved :: MIT License
Classifier: Programming Language :: Python :: 3
Classifier: Programming Language :: Python :: 3.12
Classifier: Programming Language :: Python :: 3 :: Only
Classifier: Programming Language :: Python :: 3.13
Classifier: Topic :: Scientific/Engineering :: Physics
Requires-Dist: cfspopcon (>=7.0.2)
Requires-Dist: click (>=8.2.1,<9.0.0)
Requires-Dist: ipykernel (>=6.29.5,<7.0.0)
Requires-Dist: jupyter (>=1.0.0,<2.0.0)
Requires-Dist: matplotlib (>=3.9.1,<4.0.0)
Requires-Dist: numpy (>=2.0.1,<3.0.0)
Requires-Dist: pickleshare (>=0.7.5,<0.8.0)
Requires-Dist: radas (>=2024.7.1)
Requires-Dist: scipy (>=1.14.0,<2.0.0)
